{"categories":[{"id":"b7890481-109e-41d0-9a68-61df0a5406fc","name":"Books","createdAt":1661018700281,"updatedAt":1661018700281},{"id":"da240f50-7a6b-4f2d-8286-29aded590787","name":"Sports","createdAt":1661018700281,"updatedAt":1661018700281},{"id":"c4ddce05-b590-410e-b317-aa0a57e77ec5","name":"Outdoors","createdAt":1661018700281,"updatedAt":1661018700281},{"id":"02ae470c-40a3-4b12-8888-53533cf089ec","name":"Jewelery","createdAt":1661018700282,"updatedAt":1661018700282},{"id":"a4ea4bb0-aec4-4807-8d75-d0582f3bdfaf","name":"Toys","createdAt":1661018700282,"updatedAt":1661018700282}],"products":[{"categoryId":"b7890481-109e-41d0-9a68-61df0a5406fc","id":"e88a5fd0-7e9b-41a1-b819-9f156d1e3ca2","name":"Practical Cotton Shirt","color":"ivory","price":867,"description":"The Football Is Good For Training And Recreational Purposes","createdAt":1661018700282,"updatedAt":1661018700282,"thumbnailUrl":"http://placeimg.com/400/400"},{"categoryId":"b7890481-109e-41d0-9a68-61df0a5406fc","id":"e45d3727-735f-4a37-a682-56cb79e49bfa","name":"Handmade Granite Bacon","color":"turquoise","price":255,"description":"Boston's most advanced compression wear technology increases muscle oxygenation, stabilizes active muscles","createdAt":1661018700282,"updatedAt":1661018700282,"thumbnailUrl":"http://placeimg.com/400/400"},{"categoryId":"b7890481-109e-41d0-9a68-61df0a5406fc","id":"093a9375-2309-4368-87ec-e0562e30d861","name":"Rustic Metal Shirt","color":"tan","price":553,"description":"The slim & simple Maple Gaming Keyboard from Dev Byte comes with a sleek body and 7- Color RGB LED Back-lighting for smart functionality","createdAt":1661018700282,"updatedAt":1661018700282,"thumbnailUrl":"http://placeimg.com/400/400"},{"categoryId":"b7890481-109e-41d0-9a68-61df0a5406fc","id":"20743401-cb72-4636-b267-91ccbda8b4c4","name":"Sleek Rubber Hat","color":"yellow","price":169,"description":"The Nagasaki Lander is the trademarked name of several series of Nagasaki sport bikes, that started with the 1984 ABC800J","createdAt":1661018700282,"updatedAt":1661018700282,"thumbnailUrl":"http://placeimg.com/400/400"},{"categoryId":"b7890481-109e-41d0-9a68-61df0a5406fc","id":"0f02ab7c-4a6b-4c4b-838b-e0150ba849f9","name":"Rustic Plastic Tuna","color":"violet","price":7,"description":"The beautiful range of Apple Naturalé that has an exciting mix of natural ingredients. With the Goodness of 100% Natural Ingredients","createdAt":1661018700282,"updatedAt":1661018700282,"thumbnailUrl":"http://placeimg.com/400/400"},{"categoryId":"b7890481-109e-41d0-9a68-61df0a5406fc","id":"a4c3b3c2-f322-4585-a561-e1ad2ef0392d","name":"Awesome Granite Computer","color":"cyan","price":589,"description":"The Apollotech B340 is an affordable wireless mouse with reliable connectivity, 12 months battery life and modern design","createdAt":1661018700282,"updatedAt":1661018700282,"thumbnailUrl":"http://placeimg.com/400/400"},{"categoryId":"b7890481-109e-41d0-9a68-61df0a5406fc","id":"d94a4eea-20f4-49ae-a027-30ab0064aa2a","name":"Refined Rubber Hat","color":"white","price":379,"description":"The automobile layout consists of a front-engine design, with transaxle-type transmissions mounted at the rear of the engine and four wheel drive","createdAt":1661018700282,"updatedAt":1661018700282,"thumbnailUrl":"http://placeimg.com/400/400"},{"categoryId":"b7890481-109e-41d0-9a68-61df0a5406fc","id":"aa39e789-93cf-4ad2-b57b-9aba7f07bf4b","name":"Refined Cotton Bacon","color":"yellow","price":578,"description":"New ABC 13 9370, 13.3, 5th Gen CoreA5-8250U, 8GB RAM, 256GB SSD, power UHD Graphics, OS 10 Home, OS Office A & J 2016","createdAt":1661018700282,"updatedAt":1661018700282,"thumbnailUrl":"http://placeimg.com/400/400"},{"categoryId":"b7890481-109e-41d0-9a68-61df0a5406fc","id":"4aeaab95-bfc4-4721-b0ff-ff2311fab7bf","name":"Practical Steel Sausages","color":"mint green","price":881,"description":"Carbonite web goalkeeper gloves are ergonomically designed to give easy fit","createdAt":1661018700283,"updatedAt":1661018700283,"thumbnailUrl":"http://placeimg.com/400/400"},{"categoryId":"b7890481-109e-41d0-9a68-61df0a5406fc","id":"77fe2e0d-81c1-4c76-84e5-a284adce33f4","name":"Intelligent Steel Table","color":"maroon","price":938,"description":"Ergonomic executive chair upholstered in bonded black leather and PVC padded seat and back for all-day comfort and support","createdAt":1661018700283,"updatedAt":1661018700283,"thumbnailUrl":"http://placeimg.com/400/400"},{"categoryId":"da240f50-7a6b-4f2d-8286-29aded590787","id":"c9e485bc-79cb-4fdf-84f6-38bd1f6a2c60","name":"Ergonomic Plastic Hat","color":"turquoise","price":553,"description":"Andy shoes are designed to keeping in mind durability as well as trends, the most stylish range of shoes & sandals","createdAt":1661018700283,"updatedAt":1661018700283,"thumbnailUrl":"http://placeimg.com/400/400"},{"categoryId":"da240f50-7a6b-4f2d-8286-29aded590787","id":"40860239-d9cf-44ff-95a3-dd33b0d8bfd2","name":"Rustic Soft Salad","color":"sky blue","price":823,"description":"New range of formal shirts are designed keeping you in mind. With fits and styling that will make you stand apart","createdAt":1661018700283,"updatedAt":1661018700283,"thumbnailUrl":"http://placeimg.com/400/400"},{"categoryId":"da240f50-7a6b-4f2d-8286-29aded590787","id":"f17019da-dabf-4d8d-beaa-babb75c8192f","name":"Fantastic Concrete Computer","color":"magenta","price":608,"description":"New range of formal shirts are designed keeping you in mind. With fits and styling that will make you stand apart","createdAt":1661018700283,"updatedAt":1661018700283,"thumbnailUrl":"http://placeimg.com/400/400"},{"categoryId":"da240f50-7a6b-4f2d-8286-29aded590787","id":"fa98e3e3-308a-464f-8b28-4be4465ab50f","name":"Rustic Frozen Cheese","color":"olive","price":551,"description":"The Nagasaki Lander is the trademarked name of several series of Nagasaki sport bikes, that started with the 1984 ABC800J","createdAt":1661018700283,"updatedAt":1661018700283,"thumbnailUrl":"http://placeimg.com/400/400"},{"categoryId":"da240f50-7a6b-4f2d-8286-29aded590787","id":"08db8198-99d6-456b-abfc-60b0fa796536","name":"Generic Metal Pizza","color":"cyan","price":9,"description":"The automobile layout consists of a front-engine design, with transaxle-type transmissions mounted at the rear of the engine and four wheel drive","createdAt":1661018700283,"updatedAt":1661018700283,"thumbnailUrl":"http://placeimg.com/400/400"},{"categoryId":"da240f50-7a6b-4f2d-8286-29aded590787","id":"f1d4c625-b5ed-488e-a18a-0d5ff652725b","name":"Handcrafted Frozen Tuna","color":"red","price":57,"description":"Andy shoes are designed to keeping in mind durability as well as trends, the most stylish range of shoes & sandals","createdAt":1661018700283,"updatedAt":1661018700283,"thumbnailUrl":"http://placeimg.com/400/400"},{"categoryId":"da240f50-7a6b-4f2d-8286-29aded590787","id":"a1d63d7b-423f-4e04-ac40-f5f7454262ed","name":"Licensed Plastic Towels","color":"silver","price":565,"description":"The automobile layout consists of a front-engine design, with transaxle-type transmissions mounted at the rear of the engine and four wheel drive","createdAt":1661018700283,"updatedAt":1661018700283,"thumbnailUrl":"http://placeimg.com/400/400"},{"categoryId":"da240f50-7a6b-4f2d-8286-29aded590787","id":"21e2c602-ae29-4ba9-9cf3-2edbda6cee55","name":"Unbranded Concrete Pizza","color":"black","price":16,"description":"New ABC 13 9370, 13.3, 5th Gen CoreA5-8250U, 8GB RAM, 256GB SSD, power UHD Graphics, OS 10 Home, OS Office A & J 2016","createdAt":1661018700283,"updatedAt":1661018700283,"thumbnailUrl":"http://placeimg.com/400/400"},{"categoryId":"da240f50-7a6b-4f2d-8286-29aded590787","id":"62ee7299-9f5f-4500-a5cc-ada471094869","name":"Generic Fresh Chicken","color":"black","price":356,"description":"Ergonomic executive chair upholstered in bonded black leather and PVC padded seat and back for all-day comfort and support","createdAt":1661018700283,"updatedAt":1661018700283,"thumbnailUrl":"http://placeimg.com/400/400"},{"categoryId":"da240f50-7a6b-4f2d-8286-29aded590787","id":"1ff25abb-ed56-42b0-99b2-dbec1e446d88","name":"Rustic Granite Car","color":"gold","price":690,"description":"New range of formal shirts are designed keeping you in mind. With fits and styling that will make you stand apart","createdAt":1661018700283,"updatedAt":1661018700283,"thumbnailUrl":"http://placeimg.com/400/400"},{"categoryId":"c4ddce05-b590-410e-b317-aa0a57e77ec5","id":"6b476c49-92aa-4355-9c41-b214e87658f9","name":"Practical Granite Soap","color":"violet","price":678,"description":"The automobile layout consists of a front-engine design, with transaxle-type transmissions mounted at the rear of the engine and four wheel drive","createdAt":1661018700283,"updatedAt":1661018700283,"thumbnailUrl":"http://placeimg.com/400/400"},{"categoryId":"c4ddce05-b590-410e-b317-aa0a57e77ec5","id":"9d5bfe59-6efc-4b7e-80c5-7d259f8e00c0","name":"Handmade Wooden Tuna","color":"fuchsia","price":528,"description":"New ABC 13 9370, 13.3, 5th Gen CoreA5-8250U, 8GB RAM, 256GB SSD, power UHD Graphics, OS 10 Home, OS Office A & J 2016","createdAt":1661018700283,"updatedAt":1661018700283,"thumbnailUrl":"http://placeimg.com/400/400"},{"categoryId":"c4ddce05-b590-410e-b317-aa0a57e77ec5","id":"a95e3431-c912-47d9-8089-bf2760b48915","name":"Handcrafted Fresh Soap","color":"olive","price":478,"description":"Carbonite web goalkeeper gloves are ergonomically designed to give easy fit","createdAt":1661018700283,"updatedAt":1661018700283,"thumbnailUrl":"http://placeimg.com/400/400"},{"categoryId":"c4ddce05-b590-410e-b317-aa0a57e77ec5","id":"bd3f785d-b5ca-484e-bf32-a6f12c86a7e6","name":"Practical Soft Soap","color":"sky blue","price":352,"description":"The Football Is Good For Training And Recreational Purposes","createdAt":1661018700283,"updatedAt":1661018700283,"thumbnailUrl":"http://placeimg.com/400/400"},{"categoryId":"c4ddce05-b590-410e-b317-aa0a57e77ec5","id":"0c947916-ccfb-423b-b9ad-9854f5c8a5f8","name":"Licensed Concrete Keyboard","color":"silver","price":162,"description":"Andy shoes are designed to keeping in mind durability as well as trends, the most stylish range of shoes & sandals","createdAt":1661018700283,"updatedAt":1661018700283,"thumbnailUrl":"http://placeimg.com/400/400"},{"categoryId":"c4ddce05-b590-410e-b317-aa0a57e77ec5","id":"ec695f4c-d01d-4bf1-b323-a4253ba72dd3","name":"Handcrafted Metal Chair","color":"gold","price":828,"description":"Carbonite web goalkeeper gloves are ergonomically designed to give easy fit","createdAt":1661018700283,"updatedAt":1661018700283,"thumbnailUrl":"http://placeimg.com/400/400"},{"categoryId":"c4ddce05-b590-410e-b317-aa0a57e77ec5","id":"87b1ef52-9fc5-4e5b-981f-110ae717ef5d","name":"Small Metal Chicken","color":"sky blue","price":357,"description":"Carbonite web goalkeeper gloves are ergonomically designed to give easy fit","createdAt":1661018700283,"updatedAt":1661018700283,"thumbnailUrl":"http://placeimg.com/400/400"},{"categoryId":"c4ddce05-b590-410e-b317-aa0a57e77ec5","id":"c9285243-9330-4732-b0c7-4872063bfd71","name":"Tasty Soft Sausages","color":"orange","price":825,"description":"The automobile layout consists of a front-engine design, with transaxle-type transmissions mounted at the rear of the engine and four wheel drive","createdAt":1661018700283,"updatedAt":1661018700283,"thumbnailUrl":"http://placeimg.com/400/400"},{"categoryId":"c4ddce05-b590-410e-b317-aa0a57e77ec5","id":"eb79d14d-f7af-4164-abe4-5879be996113","name":"Handmade Frozen Towels","color":"violet","price":516,"description":"Andy shoes are designed to keeping in mind durability as well as trends, the most stylish range of shoes & sandals","createdAt":1661018700285,"updatedAt":1661018700285,"thumbnailUrl":"http://placeimg.com/400/400"},{"categoryId":"c4ddce05-b590-410e-b317-aa0a57e77ec5","id":"d0160bce-5eec-4f02-8ff9-65f90cc158b9","name":"Gorgeous Fresh Shoes","color":"maroon","price":801,"description":"The Apollotech B340 is an affordable wireless mouse with reliable connectivity, 12 months battery life and modern design","createdAt":1661018700286,"updatedAt":1661018700286,"thumbnailUrl":"http://placeimg.com/400/400"},{"categoryId":"02ae470c-40a3-4b12-8888-53533cf089ec","id":"6e5f29ae-a7b8-4d1b-a937-4c71c172e0b5","name":"Generic Metal Table","color":"blue","price":611,"description":"New range of formal shirts are designed keeping you in mind. With fits and styling that will make you stand apart","createdAt":1661018700286,"updatedAt":1661018700286,"thumbnailUrl":"http://placeimg.com/400/400"},{"categoryId":"02ae470c-40a3-4b12-8888-53533cf089ec","id":"4a50abcd-0805-4808-8d3f-c4e7643fe761","name":"Ergonomic Fresh Bike","color":"magenta","price":504,"description":"The Football Is Good For Training And Recreational Purposes","createdAt":1661018700286,"updatedAt":1661018700286,"thumbnailUrl":"http://placeimg.com/400/400"},{"categoryId":"02ae470c-40a3-4b12-8888-53533cf089ec","id":"075c0602-7bc2-4afc-8768-557564984286","name":"Fantastic Wooden Chair","color":"purple","price":36,"description":"New ABC 13 9370, 13.3, 5th Gen CoreA5-8250U, 8GB RAM, 256GB SSD, power UHD Graphics, OS 10 Home, OS Office A & J 2016","createdAt":1661018700286,"updatedAt":1661018700286,"thumbnailUrl":"http://placeimg.com/400/400"},{"categoryId":"02ae470c-40a3-4b12-8888-53533cf089ec","id":"5116faa0-3c91-4d38-8c35-1128c3fcd7e7","name":"Unbranded Frozen Salad","color":"orange","price":63,"description":"The Nagasaki Lander is the trademarked name of several series of Nagasaki sport bikes, that started with the 1984 ABC800J","createdAt":1661018700286,"updatedAt":1661018700286,"thumbnailUrl":"http://placeimg.com/400/400"},{"categoryId":"02ae470c-40a3-4b12-8888-53533cf089ec","id":"44331abd-26e9-4772-a05a-610b91355749","name":"Handcrafted Wooden Sausages","color":"sky blue","price":275,"description":"New range of formal shirts are designed keeping you in mind. With fits and styling that will make you stand apart","createdAt":1661018700286,"updatedAt":1661018700286,"thumbnailUrl":"http://placeimg.com/400/400"},{"categoryId":"02ae470c-40a3-4b12-8888-53533cf089ec","id":"00902ca2-5efe-4f97-b44a-51e1e694524d","name":"Ergonomic Wooden Bike","color":"grey","price":416,"description":"New range of formal shirts are designed keeping you in mind. With fits and styling that will make you stand apart","createdAt":1661018700286,"updatedAt":1661018700286,"thumbnailUrl":"http://placeimg.com/400/400"},{"categoryId":"02ae470c-40a3-4b12-8888-53533cf089ec","id":"6ae02bd4-7d2c-4eca-9c8a-5d6068aa431e","name":"Intelligent Fresh Chair","color":"magenta","price":676,"description":"The slim & simple Maple Gaming Keyboard from Dev Byte comes with a sleek body and 7- Color RGB LED Back-lighting for smart functionality","createdAt":1661018700286,"updatedAt":1661018700286,"thumbnailUrl":"http://placeimg.com/400/400"},{"categoryId":"02ae470c-40a3-4b12-8888-53533cf089ec","id":"7095a7bc-2045-4795-9969-5c554fbe326c","name":"Sleek Rubber Fish","color":"pink","price":5,"description":"The Nagasaki Lander is the trademarked name of several series of Nagasaki sport bikes, that started with the 1984 ABC800J","createdAt":1661018700286,"updatedAt":1661018700286,"thumbnailUrl":"http://placeimg.com/400/400"},{"categoryId":"02ae470c-40a3-4b12-8888-53533cf089ec","id":"7e542f0b-731d-4914-99b1-739872beb6ac","name":"Generic Frozen Computer","color":"grey","price":988,"description":"New ABC 13 9370, 13.3, 5th Gen CoreA5-8250U, 8GB RAM, 256GB SSD, power UHD Graphics, OS 10 Home, OS Office A & J 2016","createdAt":1661018700286,"updatedAt":1661018700286,"thumbnailUrl":"http://placeimg.com/400/400"},{"categoryId":"02ae470c-40a3-4b12-8888-53533cf089ec","id":"9e60c07e-d396-46dd-bd35-05262b6cbe75","name":"Awesome Cotton Chair","color":"orchid","price":886,"description":"Andy shoes are designed to keeping in mind durability as well as trends, the most stylish range of shoes & sandals","createdAt":1661018700286,"updatedAt":1661018700286,"thumbnailUrl":"http://placeimg.com/400/400"},{"categoryId":"a4ea4bb0-aec4-4807-8d75-d0582f3bdfaf","id":"7118a830-2775-4f1f-a8d6-342f327c125e","name":"Unbranded Metal Chicken","color":"red","price":21,"description":"The Nagasaki Lander is the trademarked name of several series of Nagasaki sport bikes, that started with the 1984 ABC800J","createdAt":1661018700286,"updatedAt":1661018700286,"thumbnailUrl":"http://placeimg.com/400/400"},{"categoryId":"a4ea4bb0-aec4-4807-8d75-d0582f3bdfaf","id":"52098168-8b2a-4756-9a35-26ce838e7aab","name":"Unbranded Frozen Bacon","color":"orchid","price":364,"description":"The Nagasaki Lander is the trademarked name of several series of Nagasaki sport bikes, that started with the 1984 ABC800J","createdAt":1661018700286,"updatedAt":1661018700286,"thumbnailUrl":"http://placeimg.com/400/400"},{"categoryId":"a4ea4bb0-aec4-4807-8d75-d0582f3bdfaf","id":"6ce35a7f-f7dc-408f-af53-7f9c0fca945b","name":"Practical Metal Shoes","color":"lavender","price":974,"description":"The Nagasaki Lander is the trademarked name of several series of Nagasaki sport bikes, that started with the 1984 ABC800J","createdAt":1661018700286,"updatedAt":1661018700286,"thumbnailUrl":"http://placeimg.com/400/400"},{"categoryId":"a4ea4bb0-aec4-4807-8d75-d0582f3bdfaf","id":"47acf5e4-308d-4ae3-ad5c-8acc391627a0","name":"Sleek Granite Pants","color":"grey","price":181,"description":"The automobile layout consists of a front-engine design, with transaxle-type transmissions mounted at the rear of the engine and four wheel drive","createdAt":1661018700286,"updatedAt":1661018700286,"thumbnailUrl":"http://placeimg.com/400/400"},{"categoryId":"a4ea4bb0-aec4-4807-8d75-d0582f3bdfaf","id":"c02d07ce-f06f-4f98-ad0a-2c44f19729e7","name":"Practical Cotton Tuna","color":"fuchsia","price":476,"description":"The Football Is Good For Training And Recreational Purposes","createdAt":1661018700286,"updatedAt":1661018700286,"thumbnailUrl":"http://placeimg.com/400/400"},{"categoryId":"a4ea4bb0-aec4-4807-8d75-d0582f3bdfaf","id":"21800f15-0536-47c9-99bf-fe26e8119eec","name":"Generic Metal Pants","color":"indigo","price":500,"description":"The Football Is Good For Training And Recreational Purposes","createdAt":1661018700286,"updatedAt":1661018700286,"thumbnailUrl":"http://placeimg.com/400/400"},{"categoryId":"a4ea4bb0-aec4-4807-8d75-d0582f3bdfaf","id":"3a526da5-c131-4b3b-8e78-6bb2e640865d","name":"Intelligent Plastic Pizza","color":"tan","price":328,"description":"New ABC 13 9370, 13.3, 5th Gen CoreA5-8250U, 8GB RAM, 256GB SSD, power UHD Graphics, OS 10 Home, OS Office A & J 2016","createdAt":1661018700286,"updatedAt":1661018700286,"thumbnailUrl":"http://placeimg.com/400/400"},{"categoryId":"a4ea4bb0-aec4-4807-8d75-d0582f3bdfaf","id":"a859288a-abb9-4abd-8023-989e7b4ba277","name":"Ergonomic Rubber Sausages","color":"olive","price":710,"description":"The Nagasaki Lander is the trademarked name of several series of Nagasaki sport bikes, that started with the 1984 ABC800J","createdAt":1661018700286,"updatedAt":1661018700286,"thumbnailUrl":"http://placeimg.com/400/400"},{"categoryId":"a4ea4bb0-aec4-4807-8d75-d0582f3bdfaf","id":"efabc082-b1cb-4fbb-9c95-ddd67b54ea58","name":"Handcrafted Metal Soap","color":"cyan","price":479,"description":"Boston's most advanced compression wear technology increases muscle oxygenation, stabilizes active muscles","createdAt":1661018700286,"updatedAt":1661018700286,"thumbnailUrl":"http://placeimg.com/400/400"},{"categoryId":"a4ea4bb0-aec4-4807-8d75-d0582f3bdfaf","id":"0d76c8d8-ef9d-4019-a0ee-e06a47627f81","name":"Tasty Rubber Soap","color":"red","price":655,"description":"Andy shoes are designed to keeping in mind durability as well as trends, the most stylish range of shoes & sandals","createdAt":1661018700286,"updatedAt":1661018700286,"thumbnailUrl":"http://placeimg.com/400/400"}],"profile":{"name":"cuongnc"}}